timesynth/__init__.py
timesynth/timeseries.py
timesynth/noise/__init__.py
timesynth/noise/base_noise.py
timesynth/noise/gaussian_noise.py
timesynth/noise/red_noise.py
timesynth/signals/__init__.py
timesynth/signals/ar.py
timesynth/signals/base_signal.py
timesynth/signals/car.py
timesynth/signals/dde.py
timesynth/signals/gaussian_process.py
timesynth/signals/narma.py
timesynth/signals/ode.py
timesynth/signals/pseudoperiodic.py
timesynth/signals/sinusoidal.py
timesynth/timesampler/__init__.py
timesynth/timesampler/timesampler.py
timesynth-0.2.4.dist-info/LICENSE
timesynth-0.2.4.dist-info/METADATA
timesynth-0.2.4.dist-info/WHEEL
timesynth-0.2.4.dist-info/top_level.txt
timesynth-0.2.4.dist-info/RECORD
