Metadata-Version: 2.1
Name: timesynth
Version: 0.2.4
Summary: Library for creating synthetic time series
Home-page: https://github.com/TimeSynth/TimeSynth
Author: Abhishek Malali, Reinier Maat, Pavlos Protopapas
Author-email: anon@anon.com
License: MIT
Platform: UNKNOWN
Requires-Dist: numpy
Requires-Dist: scipy
Requires-Dist: sympy
Requires-Dist: symengine (==0.4)
Requires-Dist: jitcdde (==1.4)
Requires-Dist: jitcxde-common (==1.4.1)
